{"cameraMode":{"drawMode":0,"name":"Shaded","section":"Shading Mode"},"sceneLighting":true,"audioPlay":false,"sceneViewState":{"m_AlwaysRefresh":false,"showFog":true,"showSkybox":true,"showFlares":true,"showImageEffects":true,"showParticleSystems":true,"showVisualEffectGraphs":true,"m_FxEnabled":true},"in2DMode":false,"pivot":{"x":-2.2759904861450197,"y":1.3634769916534424,"z":2.7767813205718996},"rotation":{"x":-0.08169189840555191,"y":0.7978543043136597,"z":-0.11106006801128388,"w":-0.5868743658065796},"size":3.998427152633667,"orthographic":false}